[
  {
    "items": [
      {
        "id": "m1",
        "name": "Mac & Cheese",
        "price": "8.99",
        "description": "Creamy cheddar cheese mixed with perfectly cooked macaroni, topped with crispy breadcrumbs. A classic comfort food.",
        "image": "images/mac-and-cheese.jpg",
        "quantity": 2
      }
    ],
    "customer": {
      "name": "Aufa Syaihan Azzahidi",
      "email": "aufa.azzahidi@gmail.com",
      "street": "Banyumanik",
      "postal-code": "50267",
      "city": "Semarang"
    },
    "id": "821.0660184155989"
  }
]
